HimDonHaiDraws/__init__.py
HimDonHaiDraws/main.py
HimDonHaiDraws-0.2.dist-info/METADATA
HimDonHaiDraws-0.2.dist-info/WHEEL
HimDonHaiDraws-0.2.dist-info/top_level.txt
HimDonHaiDraws-0.2.dist-info/RECORD
