Metadata-Version: 2.1
Name: HimDonHaiDraws
Version: 0.2
Requires-Dist: turtle
Requires-Dist: sketchpy
